finphd/__init__.py
finphd/asset_pricing/__init__.py
finphd/asset_pricing/test.py
finphd/data/__init__.py
finphd/replication/__init__.py
finphd/tools/__init__.py
finphd-0.1.1.dist-info/LICENSE
finphd-0.1.1.dist-info/METADATA
finphd-0.1.1.dist-info/WHEEL
finphd-0.1.1.dist-info/RECORD
